tztrout/__init__.py
tztrout/data.py
tztrout/data_exceptions.py
tztrout/data/au_area_code_to_state.json
tztrout/data/au_state_to_tz_ids.json
tztrout/data/ca_area_code_to_state.json
tztrout/data/ca_state_to_tz_ids.json
tztrout/data/normalized_states.json
tztrout/data/offset_to_tz_ids.json
tztrout/data/tz_name_to_tz_ids.json
tztrout/data/tz_name_to_tz_name_aliases.json
tztrout/data/us_zipcode_data.json
tztrout/data/us_zips_to_tz_ids.json
tz_trout-1.0.2.dist-info/METADATA
tz_trout-1.0.2.dist-info/WHEEL
tz_trout-1.0.2.dist-info/top_level.txt
tz_trout-1.0.2.dist-info/RECORD
