Metadata-Version: 2.1
Name: tz-trout
Version: 1.0.2
Summary: Helps you figure out the time zone based on an address or a phone number.
Home-page: http://github.com/closeio/tz-trout
Author: Close.io
Author-email: engineering@close.io
Maintainer: Close.io
Maintainer-email: engineering@close.io
License: MIT
Platform: any
Classifier: Intended Audience :: Developers
Classifier: Operating System :: OS Independent
Classifier: Topic :: Software Development :: Libraries :: Python Modules
Classifier: Programming Language :: Python
Classifier: Programming Language :: Python :: 3
Requires-Python: >=3.6
Requires-Dist: phonenumbers (>=8.3.0)
Requires-Dist: python-dateutil
Requires-Dist: pytz
Provides-Extra: dev
Requires-Dist: timezonefinder ; extra == 'dev'
